README.md
setup.py
django_doc_view/__init__.py
django_doc_view/core.py
django_doc_view.egg-info/PKG-INFO
django_doc_view.egg-info/SOURCES.txt
django_doc_view.egg-info/dependency_links.txt
django_doc_view.egg-info/top_level.txt
django_doc_view/management/__init__.py
django_doc_view/management/commands/__init__.py
django_doc_view/management/commands/doc_view.py