Metadata-Version: 1.1
Name: django-doc-view
Version: 0.1.2
Summary: The simplest way to document your Django APIs
Home-page: https://github.com/ocavue/django-doc-view
Author: Ocavue
Author-email: ocavue@gmail.conm
License: MIT License
Keywords: django,api,view,document,doc
Platform: any
Classifier: Development Status :: 4 - Beta
Classifier: Programming Language :: Python :: 3
